micro_cata/__init__.py
micro_cata/compare_model.py
micro_cata/ecdf_tubulin.py
micro_cata/param_gamma.py
micro_cata-0.0.1.dist-info/.ipynb_checkpoints/requires-checkpoint.txt
micro_cata-0.0.1.dist-info/LICENSE
micro_cata-0.0.1.dist-info/METADATA
micro_cata-0.0.1.dist-info/WHEEL
micro_cata-0.0.1.dist-info/top_level.txt
micro_cata-0.0.1.dist-info/RECORD
